Metadata-Version: 2.1
Name: ddbapi
Version: 0.1.2
Summary: Library for querying DDB infrastructure
Home-page: https://gitlab.gwdg.de/becker210/ddbapi
Author: Karl Krägelin
Author-email: kraegelin@sub.uni-goettingen.de
License: MIT
Platform: UNKNOWN
Classifier: Programming Language :: Python :: 3
Requires-Python: >=3.8.5
License-File: LICENSE
